README.md
setup.cfg
setup.py
./biobox/lib/e_density.c
./biobox/lib/fastmath.c
./biobox/lib/graph.c
biobox/__init__.py
biobox/setup.py
biobox.egg-info/PKG-INFO
biobox.egg-info/SOURCES.txt
biobox.egg-info/dependency_links.txt
biobox.egg-info/requires.txt
biobox.egg-info/top_level.txt
biobox/classes/__init__.py
biobox/classes/assembly.py
biobox/classes/convex.py
biobox/classes/density.py
biobox/classes/density_MRC.py
biobox/classes/molecule.py
biobox/classes/multimer.py
biobox/classes/polyhedron.py
biobox/classes/remove_alt_conf.sh
biobox/classes/structure.py
biobox/lib/__init__.py
biobox/lib/e_den_setup.py
biobox/lib/e_density.pyx
biobox/lib/fastmath.pyx
biobox/lib/graph.pyx
biobox/measures/__init__.py
biobox/measures/calculators.py
biobox/measures/interaction.py
biobox/measures/path.py
biobox/test/EMD-1080.mrc
biobox/test/HSP.pdb
biobox/test/test_biobox.py